{"id":2925602,"title":"THINK YOU CAN TAKE ME??","posts":[{"id":49193438,"author":"GoldenMoon","registrationDate":"18 Jul 2014","publicationDate":"2018-01-07T14:24:30Z","numMessages":4818,"content":"<p><iframe id=\"ytplayer\" class=\"EmbeddedVideo\" type=\"text/html\" width=\"100%\" height=\"390\" src=\"https://youtube.com/embed/LNW93w8BLhc?html5=1&fs=1\" frameborder=\"0\" allowfullscreen webkitallowfullscreen /></iframe></p><br /><p>&nbsp;</p><br /><p>DON´T FORGET ME&nbsp;</p><br />\t\t\t\t\t</div>"},{"id":49193448,"author":"Kaim","registrationDate":"16 Feb 2007","publicationDate":"2018-01-07T14:29:22Z","numMessages":24161,"content":"<iframe id=\"ytplayer\" class=\"EmbeddedVideo\" type=\"text/html\" width=\"640\" height=\"390\" src=\"https://youtube.com/embed/nQ3hmB8s-BY?html5=1&fs=1\" frameborder=\"0\" allowfullscreen webkitallowfullscreen /></iframe>\t\t\t\t\t</div>"},{"id":49193450,"author":"Game Over","registrationDate":"23 Ago 2005","publicationDate":"2018-01-07T14:29:41Z","numMessages":36062,"content":"<p><span rel='lightbox'><img class='bbc_img' src=\"https://i.imgur.com/9BkjNCK.gif\" alt=\"9BkjNCK.gif\"></span></p><br />\t\t\t\t\t</div>"},{"id":49193461,"author":"alone snake","registrationDate":"14 Sep 2005","publicationDate":"2018-01-07T14:33:30Z","numMessages":12756,"content":"<p><iframe id=\"ytplayer\" class=\"EmbeddedVideo\" type=\"text/html\" width=\"100%\" height=\"390\" src=\"https://youtube.com/embed/qWGO8MhrEiE?html5=1&fs=1\" frameborder=\"0\" allowfullscreen webkitallowfullscreen /></iframe></p><br />\t\t\t\t\t</div>"},{"id":49193469,"author":"Rengarro","registrationDate":"31 Oct 2014","publicationDate":"2018-01-07T14:35:38Z","numMessages":3046,"content":"<iframe id=\"ytplayer\" class=\"EmbeddedVideo\" type=\"text/html\" width=\"100%\" height=\"390\" src=\"https://youtube.com/embed/AHH3s_wRvOw?html5=1&fs=1\" frameborder=\"0\" allowfullscreen webkitallowfullscreen /></iframe>\t\t\t\t\t</div>"},{"id":49193472,"author":"Kai Motoyima","registrationDate":"5 Mar 2006","publicationDate":"2018-01-07T14:36:17Z","numMessages":13422,"content":"<p>LEAVE NOPON TO POPPI</p><br />\t\t\t\t\t</div>"},{"id":49193485,"author":"Kaim","registrationDate":"16 Feb 2007","publicationDate":"2018-01-07T14:40:44Z","numMessages":24161,"content":"<iframe id=\"ytplayer\" class=\"EmbeddedVideo\" type=\"text/html\" width=\"640\" height=\"390\" src=\"https://youtube.com/embed/1Jk6YaCkjVA?html5=1&fs=1\" frameborder=\"0\" allowfullscreen webkitallowfullscreen /></iframe><br><br><br><br />2:20 es brutal. <img src='/emojis/descojone-1.gif' class='bbc_emoticon' alt='X-D' />\t\t\t\t\t</div>"},{"id":49193924,"author":"Jex04_Gaditano","registrationDate":"7 Ago 2003","publicationDate":"2018-01-07T16:49:04Z","numMessages":46659,"content":"Hams.\t\t\t\t\t</div>"},{"id":49193953,"author":"Franchuzas","registrationDate":"2 Mar 2007","publicationDate":"2018-01-07T16:55:12Z","numMessages":18100,"content":"<p>Y después hay gente que quiere jugar a Xenoblade 1 y 2 en japonés. No sois dignos de los buenos memes.</p><br />\t\t\t\t\t</div>"},{"id":49193969,"author":"changomingo","registrationDate":"29 Oct 2012","publicationDate":"2018-01-07T16:59:35Z","numMessages":13611,"content":"<p>Debe ser el juego que menos me apeatece jugar cuanto lo veo en videos.</p><br /><p>&nbsp;</p><br /><p>&nbsp;</p><br /><p>Ya luego lo juegas y te das cuenta del pedazo de combate y posibilidades que hay, al menos con el Xenoblade 1.</p><br />\t\t\t\t\t</div>"},{"id":49193977,"author":"Grimgor Ironhide","registrationDate":"22 Ago 2017","publicationDate":"2018-01-07T17:01:12Z","numMessages":4730,"content":"<p><span rel='lightbox'><img class='bbc_img' src=\"https://i.gyazo.com/a3717c91476b1ff69766577233f40a7c.png\" alt=\"a3717c91476b1ff69766577233f40a7c.png\"></span></p><br />\t\t\t\t\t</div>"},{"id":49193993,"author":"Sir_Dekar","registrationDate":"7 Jul 2008","publicationDate":"2018-01-07T17:04:56Z","numMessages":54061,"content":"<p>Pues sólo he estado jugando en japones y ni me he enterado sobre esto...</p><br /><p>&nbsp;</p><br /><p>De hecho las veces anteriores que postearon ese video no lo quise ver, pensando en que podía ser un spoiler <img src='/emojis/descojone-1.gif' class='bbc_emoticon' alt='X-D' />&nbsp;.</p><br />\t\t\t\t\t</div>"},{"id":49193994,"author":"alcabcucu","registrationDate":"24 Ago 2007","publicationDate":"2018-01-07T17:05:08Z","numMessages":28125,"content":"<p><img src='/emojis/descojone-1.gif' class='bbc_emoticon' alt='X-D' /></p><br />\t\t\t\t\t</div>"},{"id":49194797,"author":"Choco Love","registrationDate":"1 Dic 2005","publicationDate":"2018-01-07T21:07:38Z","numMessages":12509,"content":"<p>I like your attitude.</p><br />\t\t\t\t\t</div>"},{"id":49194804,"author":"Sarjon","registrationDate":"7 May 2013","publicationDate":"2018-01-07T21:10:32Z","numMessages":11359,"content":"<blockquote data-ipsquote=\"\" class=\"ipsQuote\" data-ipsquote-contentcommentid=\"49193969\" data-ipsquote-username=\"changomingo\" data-cite=\"changomingo\" data-ipsquote-timestamp=\"1515344375\"><div><p></p><div><p></p><p>Debe ser el juego que menos me apeatece jugar cuanto lo veo en videos.</p><p></p><p> </p><p></p><p> </p><p></p><p>Ya luego lo juegas y te das cuenta del pedazo de combate y posibilidades que hay, al menos con el Xenoblade 1.</p><p></p></div><p></p></div></blockquote><p></p><p>A mi me pasa lo mismo, mira que me gusta la saga, especialmente el primero, pero es ver esto, que tampoco es que haya visto mucho salvo el primer trailer y punto, y me da bajona. No se, en cuanto termine con Odyssey será el siguiente en mi lista, pero desde luego mi hype está bajo mínimos, lo cual puede ser bueno, a poco que me sorprenda ya me tendrá ganado.</p><p></p><p> </p><p></p><p>Lo del video, pues ni puta gracia, debo ser ya un puto viejo amargado.</p>\t\t\t\t\t</div>"},{"id":49194809,"author":"Leader Protoss","registrationDate":"9 Ene 2005","publicationDate":"2018-01-07T21:12:18Z","numMessages":15965,"content":"<p><iframe id=\"ytplayer\" class=\"EmbeddedVideo\" type=\"text/html\" width=\"100%\" height=\"390\" src=\"https://youtube.com/embed/SaMvjQZRTfw?html5=1&fs=1\" frameborder=\"0\" allowfullscreen webkitallowfullscreen /></iframe></p><br />\t\t\t\t\t</div>"},{"id":49194822,"author":"adriM21","registrationDate":"22 Nov 2016","publicationDate":"2018-01-07T21:13:49Z","numMessages":715,"content":"<p>Magistral xDDDD</p>\t\t\t\t\t</div>"},{"id":49194862,"author":"Kaim","registrationDate":"16 Feb 2007","publicationDate":"2018-01-07T21:21:12Z","numMessages":24161,"content":"<blockquote data-ipsquote=\"\" class=\"ipsQuote\" data-ipsquote-contentcommentid=\"49194804\" data-ipsquote-username=\"Sarjon\" data-cite=\"Sarjon\" data-ipsquote-timestamp=\"1515359432\"><div><p>A mi me pasa lo mismo, mira que me gusta la saga, especialmente el primero, pero es ver esto, que tampoco es que haya visto mucho salvo el primer trailer y punto, y me da bajona. No se, en cuanto termine con Odyssey será el siguiente en mi lista, pero desde luego mi hype está bajo mínimos, lo cual puede ser bueno, a poco que me sorprenda ya me tendrá ganado.</p><p> </p><p>Lo del video, pues ni puta gracia, debo ser ya un puto viejo amargado.</p></div></blockquote><p>El sistema de combate me animaría a decir que es lo mejor del juego. Yo lo disfruté más que el del primero, la verdad. Está muy bien, hubiese preferido otro sistema de obtención de blades, pero eso es personalización, lo que es exclusivamente dentro del combate, cero quejas (más dificultad a lo sumo).</p><p> </p><p>Lo que si te diría es que vayas con cautela con la historia, que igual te encanta, pero tiene un tono muy distinto al del primero.</p><p> </p><p>Si no te ríes con el majete de Etika (principalmente en el 2:20 xD) es que si, ya estás viejuno. <img alt=\":P\" data-src=\"http://meristation.as.com/zonaforo/uploads/emoticons/default_lengua.gif\" src=\"http://meristation.as.com/zonaforo/applications/core/interface/js/spacer.png\"></p><p> </p><p> </p><p><iframe id=\"ytplayer\" class=\"EmbeddedVideo\" type=\"text/html\" width=\"640\" height=\"390\" frameborder=\"0\" allowfullscreen webkitallowfullscreen data-embed-src=\"https://youtube.com/embed/1Jk6YaCkjVA?html5=1&amp;fs=1\"></iframe></p>\t\t\t\t\t</div>"},{"id":49194938,"author":"Sarjon","registrationDate":"7 May 2013","publicationDate":"2018-01-07T21:31:44Z","numMessages":11359,"content":"<blockquote data-ipsquote=\"\" class=\"ipsQuote\" data-ipsquote-contentcommentid=\"49194862\" data-ipsquote-username=\"Kaim\" data-cite=\"Kaim\" data-ipsquote-timestamp=\"1515360072\"><div><p></p><div><p></p><p>El sistema de combate me animaría a decir que es lo mejor del juego. Yo lo disfruté más que el del primero, la verdad. Está muy bien, hubiese preferido otro sistema de obtención de blades, pero eso es personalización, lo que es exclusivamente dentro del combate, cero quejas (más dificultad a lo sumo).</p><p> </p><p> </p><p>Lo que si te diría es que vayas con cautela con la historia, que igual te encanta, pero tiene un tono muy distinto al del primero.</p><p> </p><p> </p><p>Si no te ríes con el majete de Etika (principalmente en el 2:20 xD) es que si, ya estás viejuno. <img alt=\":P\" data-src=\"http://meristation.as.com/zonaforo/uploads/emoticons/default_lengua.gif\" src=\"http://meristation.as.com/zonaforo/applications/core/interface/js/spacer.png\"></p><p> </p><p> </p><p> </p><p><iframe id=\"ytplayer\" class=\"EmbeddedVideo\" type=\"text/html\" width=\"640\" height=\"390\" frameborder=\"0\" allowfullscreen webkitallowfullscreen data-embed-src=\"https://youtube.com/embed/1Jk6YaCkjVA?html5=1&amp;fs=1\"></iframe></p><p></p></div><p></p></div></blockquote><p></p><p>Gracias por el comentario, la verdad es que es precisamente el tono de la historia del primer Xenoblade lo que más me gustaba, pero bueno, mientras el sistema de combate sea bueno por mi perfecto.</p><p></p><p>Los escenarios que tal? Igual de grandes y explorables? Es que lo poco que he visto me parece tan poco llamativo...</p><p></p><p> </p><p></p><p>Y si, estoy viejuno, no se, es típico que los personajes siempre repitan las mismas frases, si encima te encuentras con tres iguales pues... No se me parece un intento forzado de crear un meme, de todas formas creo que después de oir lo de \"me estás nombrando virreina\" ya todo lo demás dejó de tener gracia. Aunque bueno, no acabo de cogerle el significado a \"no me olvides\" en ese contexto, quizás me esté empezando a hacer gracia XD</p><p> </p>\t\t\t\t\t</div>"},{"id":49195024,"author":"Kaim","registrationDate":"16 Feb 2007","publicationDate":"2018-01-07T21:40:29Z","numMessages":24161,"content":"<p><iframe id=\"ytplayer\" class=\"EmbeddedVideo\" type=\"text/html\" width=\"100%\" height=\"390\" frameborder=\"0\" allowfullscreen webkitallowfullscreen data-embed-src=\"https://youtube.com/embed/_yYf-tV79tQ?html5=1&amp;fs=1\"></iframe></p><p> </p><p> </p><p></p><blockquote data-ipsquote=\"\" class=\"ipsQuote\" data-ipsquote-contentcommentid=\"49194938\" data-ipsquote-username=\"Sarjon\" data-cite=\"Sarjon\" data-ipsquote-timestamp=\"1515360704\"><div><p>Gracias por el comentario, la verdad es que es precisamente el tono de la historia del primer Xenoblade lo que más me gustaba, pero bueno, mientras el sistema de combate sea bueno por mi perfecto.</p><p>Los escenarios que tal? Igual de grandes y explorables? Es que lo poco que he visto me parece tan poco llamativo...</p><p> </p><p>Y si, estoy viejuno, no se, es típico que los personajes siempre repitan las mismas frases, si encima te encuentras con tres iguales pues... No se me parece un intento forzado de crear un meme, de todas formas creo que después de oir lo de \"me estás nombrando virreina\" ya todo lo demás dejó de tener gracia. Aunque bueno, no acabo de cogerle el significado a \"no me olvides\" en ese contexto, quizás me esté empezando a hacer gracia XD</p></div></blockquote><p> </p><p>En temas de escenarios y exploración va muy en la linea del primero (salvo cuando entran en juego las competencias, eso es lo puto peor) y artísticamente sus escenarioss están muy bien, dudo que te decepcione en ese sentido si disfrutaste del primero.</p>\t\t\t\t\t</div>"},{"id":49195244,"author":"Sir_Dekar","registrationDate":"7 Jul 2008","publicationDate":"2018-01-07T22:40:05Z","numMessages":54061,"content":"<p>Que me perdonen los fans de Persona, pero el tema de batalla de Persona 5 está casi al nivel del tema de noche de New Los Angeles en Xenoblade Chronicles 2...</p><br /><p>&nbsp;</p><br /><p><iframe id=\"ytplayer\" class=\"EmbeddedVideo\" type=\"text/html\" width=\"100%\" height=\"390\" src=\"https://youtube.com/embed/c_N7WgxEoI8?html5=1&fs=1\" frameborder=\"0\" allowfullscreen webkitallowfullscreen /></iframe></p><br /><p>&nbsp;</p><br /><p>Luego este tema está mucho mejor:</p><br /><p>&nbsp;</p><br /><p><iframe id=\"ytplayer\" class=\"EmbeddedVideo\" type=\"text/html\" width=\"100%\" height=\"390\" src=\"https://youtube.com/embed/GrbnhjNQM3A?html5=1&fs=1\" frameborder=\"0\" allowfullscreen webkitallowfullscreen /></iframe></p><br />\t\t\t\t\t</div>"},{"id":49195263,"author":"alcabcucu","registrationDate":"24 Ago 2007","publicationDate":"2018-01-07T22:52:49Z","numMessages":28125,"content":"<blockquote data-ipsquote=\"\" class=\"ipsQuote\" data-ipsquote-contentcommentid=\"49194804\" data-ipsquote-username=\"Sarjon\" data-cite=\"Sarjon\" data-ipsquote-timestamp=\"1515359432\"><div><p></p><div><p></p><p>A mi me pasa lo mismo, mira que me gusta la saga, especialmente el primero, pero es ver esto, que tampoco es que haya visto mucho salvo el primer trailer y punto, y me da bajona. No se, en cuanto termine con Odyssey será el siguiente en mi lista, pero desde luego mi hype está bajo mínimos, lo cual puede ser bueno, a poco que me sorprenda ya me tendrá ganado.</p><p></p><p> </p><p></p><p>Lo del video, pues ni puta gracia, debo ser ya un puto viejo amargado.</p><p></p></div><p></p></div></blockquote><p></p><p>Hay que andarse con ojo aquí. La historia tiene una capa muy shonen, sobre todo al principio, que puede acabar saturando e incluso destrozar la experiencia de juego. Pero si rascas un poco, descubrirás que debajo hay mucha chicha.</p><p></p><p> </p><p></p><p>Por otro lado, yo diría que los escenarios son algo menos complejos que en la primera entrega, aunque algunos son realmente memorables. El universo de Alrest me ha cautivado tanto como el de Mekonis y Bionis, y su historia \"política\" es mucho más compleja. El elenco protagonista, tanto de héroes como de villanos, es sensacional. De verdad. Sensacional.</p><p></p><p> </p><p></p><p>Lo que no comparto con Kaim es la cuestión de la gestión de los blades, que a mí me ha encantado y le dan una personalidad distinta al juego. Es una gozada hacerse con todos ellos e ir mejorándolos siguiendo una progresión de logros que incluye misiones específicas para casi cada uno de ellos. Además su razón de ser está perfectamente integrada en el universo que despliega el juego.</p><p></p><p> </p><p></p><p>El sistema de combate -para mí- es una obra de arte.</p><p></p><p> </p><p></p><p>En lo personal, pienso que es un juego más potente que el primer Xenoblade, pero su disfraz puede acabar consiguiendo que no veamos lo que esconde debajo. A mí me ha gustado mucho, aunque me costó entrar en él al principio precisamente por aquello que lo diferencia de los anteriores. Eso sí, nada iguala todavía el sistema de afinigramas de los habitantes de los poblados que vimos en el primero.</p><p></p><p> </p><p></p><p>Un saludo.</p><p></p><p> </p><p></p><p>PD: Lo de las competencias que comenta Kaim sin duda van a tener que pulirlo. Pero quiero verlo de nuevo en futuras entregas, a ser posible mejor depurado.</p><p> </p>\t\t\t\t\t</div>"},{"id":49195297,"author":"SSJTokaidin","registrationDate":"2 Mar 2017","publicationDate":"2018-01-07T23:04:40Z","numMessages":5604,"content":"<p><iframe id=\"ytplayer\" class=\"EmbeddedVideo\" type=\"text/html\" width=\"100%\" height=\"390\" src=\"https://youtube.com/embed/MjlMiVhwSkc?html5=1&fs=1\" frameborder=\"0\" allowfullscreen webkitallowfullscreen /></iframe></p><br />\t\t\t\t\t</div>"},{"id":49195358,"author":"Kaim","registrationDate":"16 Feb 2007","publicationDate":"2018-01-07T23:32:52Z","numMessages":24161,"content":"<blockquote data-ipsquote=\"\" class=\"ipsQuote\" data-ipsquote-contentcommentid=\"49195263\" data-ipsquote-username=\"alcabcucu\" data-cite=\"alcabcucu\" data-ipsquote-timestamp=\"1515365569\"><div><p></p><p>Hay que andarse con ojo aquí. La historia tiene una capa muy shonen, sobre todo al principio, que puede acabar saturando e incluso destrozar la experiencia de juego. Pero si rascas un poco, descubrirás que debajo hay mucha chicha.</p><p> </p><p> </p><p> </p><p>Por otro lado, yo diría que los escenarios son algo menos complejos que en la primera entrega, aunque algunos son realmente memorables. El universo de Alrest me ha cautivado tanto como el de Mekonis y Bionis, y su historia \"política\" es mucho más compleja. El elenco protagonista, tanto de héroes como de villanos, es sensacional. De verdad. Sensacional.</p><p> </p><p> </p><p> </p><p>Lo que no comparto con Kaim es la cuestión de la gestión de los blades, que a mí me ha encantado y le dan una personalidad distinta al juego. Es una gozada hacerse con todos ellos e ir mejorándolos siguiendo una progresión de logros que incluye misiones específicas para casi cada uno de ellos. Además su razón de ser está perfectamente integrada en el universo que despliega el juego.</p><p> </p><p> </p><p> </p><p>El sistema de combate -para mí- es una obra de arte.</p><p> </p><p> </p><p> </p><p>En lo personal, pienso que es un juego más potente que el primer Xenoblade, pero su disfraz puede acabar consiguiendo que no veamos lo que esconde debajo. A mí me ha gustado mucho, aunque me costó entrar en él al principio precisamente por aquello que lo diferencia de los anteriores. Eso sí, nada iguala todavía el sistema de afinigramas de los habitantes de los poblados que vimos en el primero.</p><p> </p><p> </p><p> </p><p>Un saludo.</p><p> </p><p> </p><p> </p><p>PD: Lo de las competencias que comenta Kaim sin duda van a tener que pulirlo. Pero quiero verlo de nuevo en futuras entregas, a ser posible mejor depurado.</p><p></p></div></blockquote><p> </p><p></p><p>Yo hubiese preferido otro sistema para obtener blades. El que tiene es el gacha de los juegos de móviles pero más rancio aún debido a que es individual por personaje y el objeto para traspasar blades entre ellos es escasísimo (hasta los f2p de móviles son más bondadosos con el jugador en ese sentido). Había miles de formas de hacerlo más interesante (me repito, pero los SMT/Persona son un claro ejemplo).</p><p></p><p> </p><p></p><p>A eso se le suman los afinigramas, las competencias, las misiones merc-merc, todas ideas que a priori son interesantes (y comparto el sentimiento de volver a verlas en futuras entregas pero mejor desarrolladas) pero que en el juego están fatalmente ejecutadas.</p><p></p><p> </p><p></p><p>No es divertido que te obliguen a hablar con 40 NPCs, o usar 7 veces un objeto en la alforja o matar 5 arañas (cuando ya lo has hecho pero no cuenta porque justo en ese momento no tenías ese blade) por el simple hecho de desarrollar un afinigrama y conseguir una competencia. Ni hablar las peticiones que te obligan a usar las misiones merc-merc, estar pendiente 30-40-50 minutos solo por eso. Todo eso es tedioso y aburrido, han ido a lo fácil en ese sentido y la han cagado. Hay otras que son más ingeniosas y te obligan a dominar mejor el sistema de combate, por ejemplo lograr una puntuación de 20000 en un combo de blade, pero son las menos. Pienso que el desarrollo de los afinigramas tendría que ser más ingenioso y divertido, y como no lo es impacta de lleno en la idea de las competencias, que al final cuando te encuentras con una barrera de competencia ya estás acordandote de la familia de los desarrolladores. </p><p></p><p> </p><p></p><p>Son cosas que por suerte impactan muy poco en el recorrido principal (no más que un puñado de veces), pero que a poco que te desvíes de él estás chocando con esa barrera constantemente. Y en lo personal pienso que mi viaje en XC2 está terminando en estas 70hs y es que por más que me quiera seguir empapando en su bonito mundo, disfrutando de su sistema de combate y música, es ponerme a hacer alguna secundaria y chocar constantemente con ese tipo de obstáculos y pésimas decisiones de diseño y es inevitable caer en el tedio. Y prefiero no arruinarme el buen sabor de boca que me dejó el recorrido principal. <img alt=\"X-D\" data-src=\"http://meristation.as.com/zonaforo/uploads/emoticons/default_descojone-1.gif\" src=\"http://meristation.as.com/zonaforo/applications/core/interface/js/spacer.png\"></p><p></p><p> </p><p> </p>\t\t\t\t\t</div>"},{"id":49195394,"author":"alcabcucu","registrationDate":"24 Ago 2007","publicationDate":"2018-01-07T23:55:56Z","numMessages":28125,"content":"<p>A mí el sistema de afinigramas, más que divertido, me parece tremendamente adictivo. Al final, es el mismo sistema que en el primero, pero en lugar de incidir sobre las relaciones de lo habitantes de Bionis, lo hace sobre el desarrollo de los Blades mediante \"misiones\" indirectas (o logros). A mí me tiene enganchadísimo. Y seguramente por eso también lo de las competencias me ha resultado muy satisfactorio.</p><br /><p>&nbsp;</p><br /><p>Como ya te comenté cuando hablábamos del primer Xenoblade, me parece un mecanismo estupendo para estimular y fomentar los combates mediante un sistema de recompensas mucho más elaborado que la mera obtención de experiencia.</p><br /><p>&nbsp;</p><br /><p>Respecto a las misiones Merc-Merc, ahí está claro que queda muy lejos del sistema de explotación de sondas que tan bien funcionaba en X.</p><br /><p>&nbsp;</p><br /><p>Recibe un cordial saludo.</p>\t\t\t\t\t</div>"},{"id":49195411,"author":"Kaim","registrationDate":"16 Feb 2007","publicationDate":"2018-01-08T00:07:29Z","numMessages":24161,"content":"<p>Es que no funciona como el primero, funciona peor. Si en XC1 casi que se iban resolviendo \"solas\" por el simple hecho de explorar como dices (algo con lo que no coincido, pero vamos a tomarlo como válido), aquí tienes que tener la intención deliberada de hacer esa tarea tediosa si o si, porque difícilmente vayas a hacer eso desinteresadamente. Menos cuando te equipas otro blade y te pide lo mismo que el anterior pero no vale que ya lo hayas hecho con ese otro blade. Es decir, un blade te pide que hables con 50 Nopons, lo haces (intencionada o casualmente) y evolucionas su afinigrama. Conseguís a otro blade que también te pide que hables con 50 Nopons y el recuento va a cero, no tiene en cuenta que lo hayas hecho con otro...Yo desde luego me hubiese divertido más evolucionar sus afinigramas disfrutando su sistema de combate que cumpliendo con ese tipo de tareas tediosas. En fin, me parece pésimamente ejecutado.</p><br />\t\t\t\t\t</div>"},{"id":49195425,"author":"alone snake","registrationDate":"14 Sep 2005","publicationDate":"2018-01-08T00:13:52Z","numMessages":12756,"content":"<blockquote data-ipsquote=\"\" class=\"ipsQuote\" data-ipsquote-contentcommentid=\"49195411\" data-ipsquote-username=\"Kaim\" data-cite=\"Kaim\" data-ipsquote-timestamp=\"1515370049\"><div><p></p><div><p></p><p>Es que no funciona como el primero, funciona peor. Si en XC1 casi que se iban resolviendo \"solas\" por el simple hecho de explorar como dices (algo con lo que no coincido, pero vamos a tomarlo como válido), aquí tienes que tener la intención deliberada de hacer esa tarea tediosa si o si, porque difícilmente vayas a hacer eso desinteresadamente. Menos cuando te equipas otro blade y te pide lo mismo que el anterior pero no vale que ya lo hayas hecho con ese otro blade. Es decir, un blade te pide que hables con 50 Nopons, lo haces (intencionada o casualmente) y evolucionas su afinigrama. Conseguís a otro blade que también te pide que hables con 50 Nopons y el recuento va a cero, no tiene en cuenta que lo hayas hecho con otro...Yo desde luego me hubiese divertido más evolucionar sus afinigramas disfrutando su sistema de combate que cumpliendo con ese tipo de tareas tediosas. En fin, me parece pésimamente ejecutado.</p><p></p></div><p></p></div></blockquote><p></p><p> </p><p></p><p>Muchos de esos encargos, como hablar con X personas, rescatar X tesoros buceando, cocinar, etc.. siempre te cuenta lo anterior. No hay reinicio de Cero ni nada por el estilo.</p>\t\t\t\t\t</div>"},{"id":49195444,"author":"Kai Motoyima","registrationDate":"5 Mar 2006","publicationDate":"2018-01-08T00:26:41Z","numMessages":13422,"content":"<p>Citadme mañana este mensaje para entrar el debate con Kaim y alcabcucu que ahora tengo sueño <img src='/emojis/descojone-1.gif' class='bbc_emoticon' alt='X-D' />.</p><br />\t\t\t\t\t</div>"},{"id":49195445,"author":"Kaim","registrationDate":"16 Feb 2007","publicationDate":"2018-01-08T00:26:45Z","numMessages":24161,"content":"<blockquote data-ipsquote=\"\" class=\"ipsQuote\" data-ipsquote-contentcommentid=\"49195425\" data-ipsquote-username=\"alone snake\" data-cite=\"alone snake\" data-ipsquote-timestamp=\"1515370432\"><div><p></p><div><p></p><p>Muchos de esos encargos, como hablar con X personas, rescatar X tesoros buceando, cocinar, etc.. siempre te cuenta lo anterior. No hay reinicio de Cero ni nada por el estilo.</p><p></p></div><p></p></div></blockquote><p></p><p> </p><p></p><p>No, o estás hablando de otra cosa. Si hablaste con 50 Nopons y completaste la rama de \"Cultura Nopon\" con un Blade, si te sale otro Blade que tiene \"Cultura Nopon\" vas a tener que volver a hablar con 50 Nopons.</p><p> </p>\t\t\t\t\t</div>"},{"id":49195456,"author":"jordavser","registrationDate":"1 Abr 2007","publicationDate":"2018-01-08T00:34:14Z","numMessages":39826,"content":"<blockquote data-ipsquote=\"\" class=\"ipsQuote\" data-ipsquote-contentcommentid=\"49195411\" data-ipsquote-username=\"Kaim\" data-cite=\"Kaim\" data-ipsquote-timestamp=\"1515370049\"><div><p> </p><p>Es que no funciona como el primero, funciona peor. Si en XC1 casi que se iban resolviendo \"solas\" por el simple hecho de explorar como dices (algo con lo que no coincido, pero vamos a tomarlo como válido), aquí tienes que tener la intención deliberada de hacer esa tarea tediosa si o si, porque difícilmente vayas a hacer eso desinteresadamente. Menos cuando te equipas otro blade y te pide lo mismo que el anterior pero no vale que ya lo hayas hecho con ese otro blade. Es decir, un blade te pide que hables con 50 Nopons, lo haces (intencionada o casualmente) y evolucionas su afinigrama. Conseguís a otro blade que también te pide que hables con 50 Nopons y el recuento va a cero, no tiene en cuenta que lo hayas hecho con otro...Yo desde luego me hubiese divertido más evolucionar sus afinigramas disfrutando su sistema de combate que cumpliendo con ese tipo de tareas tediosas. En fin, me parece pésimamente ejecutado.</p></div></blockquote><p> </p><p> </p><p>Precisamente muchos de esos logros se consiguen luchando (te piden que uses un especial concreto, combos blade, combos de piloto...) y muchos se consiguen solos. Para eso están también las misiones de mercenarios, y no veo que tengas que estar pendiente. Mandas a un grupo a una misión y mientras tanto vas haciendo otras cosas. Unos cuantos afinigramas he rellenado así.</p><p> </p><p> </p><p>Respecto a los logros de hablar con NPCs, tampoco es nada del otro mundo. Lo de hablar con 50 nopons en unos pocos minutos se hace (coges 2 nopons y les hablas repetidamente alternándolos).</p><p> </p><p> </p><p>Los peores logros para mí son los de cocinar/tallar/repostería... Que por suerte tampoco son demasiados.</p><p> </p><p> </p><p> </p><p>Lo que sí creo que deberían mejorar es las competencias. A la hora de explorar, cuando tienes que hacer uso de las competencias deberían haber hecho que el juego detectara si cumples el requisito con todos los blades que tengas en ese momento y no solo los blades equipados.</p>\t\t\t\t\t</div>"},{"id":49195459,"author":"alcabcucu","registrationDate":"24 Ago 2007","publicationDate":"2018-01-08T00:36:06Z","numMessages":28125,"content":"<blockquote data-ipsquote=\"\" class=\"ipsQuote\" data-ipsquote-contentcommentid=\"49195445\" data-ipsquote-username=\"Kaim\" data-cite=\"Kaim\" data-ipsquote-timestamp=\"1515371205\"><div><p></p><div><p></p><p>No, o estás hablando de otra cosa. Si hablaste con 50 Nopons y completaste la rama de \"Cultura Nopon\" con un Blade, si te sale otro Blade que tiene \"Cultura Nopon\" vas a tener que volver a hablar con 50 Nopons.</p><p></p></div><p></p></div></blockquote><p></p><p>Pero te refieres a blades únicos o a los blade normales?</p><p></p><p> </p><p></p><p>Yo no he desarrollado voluntariamente ni un solo blade normal. Con las misiones Merc-Merc me ha bastado.</p><p></p><p> </p><p></p><p>En el caso de los Blades únicos, que yo recuerde eso no me ha pasado. Precisamente lo de las conversaciones con las distintas razas se me ha ido desbloqueando prácticamente sin que me diera cuenta y sin recurrir al truco -tramposo <img alt=\"X-D\" data-src=\"http://meristation.as.com/zonaforo/uploads/emoticons/default_descojone-1.gif\" src=\"http://meristation.as.com/zonaforo/applications/core/interface/js/spacer.png\">- que comenta jordavser. Es cuestión de ir jugando para obtener según qué logros, sin obsesionarse. </p><p></p><p>Pero en el caso de los blade únicos, no recuerdo que se repitiera un logro similar entre los que tenían cultura nopón (aunque todavía me faltan 3 por conseguir). Con cultura nopón así de memoria diría que tengo a Boreas, Poppi, y alguno más. Y lo de hablar con 50 nopón, que yo recuerde, solo pasaba en el caso de Boreas.</p><p></p><p> </p><p></p><p>Un saludo.</p><p> </p>\t\t\t\t\t</div>"},{"id":49195468,"author":"Kaim","registrationDate":"16 Feb 2007","publicationDate":"2018-01-08T00:43:21Z","numMessages":24161,"content":"<p>Por supuesto hablo de los blades raros. Y dí ese ejemplo por dar uno y porque justo me pasó que ese logro lo había cumplido hace rato con Popi y ahora me salió Boreas y el logro de Nopon está en 0/50. <img alt=\"X-D\" data-src=\"http://meristation.as.com/zonaforo/uploads/emoticons/default_descojone-1.gif\" src=\"http://meristation.as.com/zonaforo/applications/core/interface/js/spacer.png\"></p><br><p> </p><br><p> </p><br><blockquote data-ipsquote=\"\" class=\"ipsQuote\" data-ipsquote-contentcommentid=\"49195444\" data-ipsquote-username=\"Kai Motoyima\" data-cite=\"Kai Motoyima\" data-ipsquote-timestamp=\"1515371201\"><div><br><div><br><p>Citadme mañana este mensaje para entrar el debate con Kaim y alcabcucu que ahora tengo sueño <img alt=\"X-D\" data-src=\"http://meristation.as.com/zonaforo/uploads/emoticons/default_descojone-1.gif\" src=\"http://meristation.as.com/zonaforo/applications/core/interface/js/spacer.png\">.</p><br></div><br></div></blockquote><br><p> </p><br><p></p><div class=\"ipsSpoiler\" data-ipsspoiler=\"\"><div class=\"ipsSpoiler_header\"><span>Spoiler</span></div><div class=\"ipsSpoiler_contents\">Don't forget me.</div></div><br>\t\t\t\t\t</div>"},{"id":49195469,"author":"Sirya","registrationDate":"7 Ene 2017","publicationDate":"2018-01-08T00:44:52Z","numMessages":12747,"content":"<p>Diría que es pesado de cojones, pero es que todavía resuena en mi cabeza la puta frase de Kosm.</p><br />\t\t\t\t\t</div>"},{"id":49195479,"author":"alcabcucu","registrationDate":"24 Ago 2007","publicationDate":"2018-01-08T01:02:48Z","numMessages":28125,"content":"<blockquote data-ipsquote=\"\" class=\"ipsQuote\" data-ipsquote-contentcommentid=\"49195468\" data-ipsquote-username=\"Kaim\" data-cite=\"Kaim\" data-ipsquote-timestamp=\"1515372201\"><div><p></p><div><p></p><p>Por supuesto hablo de los blades raros. Y dí ese ejemplo por dar uno y porque justo me pasó que ese logro lo había cumplido hace rato con Popi y ahora me salió Boreas y el logro de Nopon está en 0/50. <img alt=\"X-D\" data-src=\"http://meristation.as.com/zonaforo/uploads/emoticons/default_descojone-1.gif\" src=\"http://meristation.as.com/zonaforo/applications/core/interface/js/spacer.png\"></p><p></p><p> </p><p></p><p> </p><p></p><p> </p><p></p><p></p><div class=\"ipsSpoiler\" data-ipsspoiler=\"\"><div class=\"ipsSpoiler_header\"><span>Spoiler</span></div><div class=\"ipsSpoiler_contents\">Don't forget me.</div></div><p></p></div><p></p></div></blockquote><p></p><p>Acabo de comprobarlo porque me has picado la curiosidad y veo que tienes razón.</p><p></p><p>Lo sé porque</p><p></p><p> </p><p></p><p></p><div class=\"ipsSpoiler\" data-ipsspoiler=\"\"><div class=\"ipsSpoiler_header\"><span>Spoiler</span></div><div class=\"ipsSpoiler_contents\"> A Theory no la tengo desarrollada todavía y veo que para subirle la cultura nopón hay que hablar con 30 nopón... Eso sí, tengo peinado todo el juego -o eso creo- y diría que el máximo necesario de cultura nopón es 7 puntos. Pude alcanzarlos con Poppi y Boreas a 3, y Theory a 1. La verdad es que por lo que veo tuve suerte y no es una competencia con la que tuviera que \"farmear\" nada. La que sí me hizo sudar fue la dichosa concentración en la misión de la escuela. Básicamente porque había que desarrollar confianza y en aquellos momentos la tenía baja con uno de los blade necesarios. </div></div><p></p><p> </p><p></p><p>Un saludo.</p><p> </p>\t\t\t\t\t</div>"},{"id":49195512,"author":"DarkJM","registrationDate":"18 Ago 2009","publicationDate":"2018-01-08T01:50:30Z","numMessages":9110,"content":"<blockquote data-ipsquote=\"\" class=\"ipsQuote\" data-ipsquote-contentcommentid=\"49195411\" data-ipsquote-username=\"Kaim\" data-cite=\"Kaim\" data-ipsquote-timestamp=\"1515370049\"><div><p></p><div><p></p><p>Es que no funciona como el primero, funciona peor. Si en XC1 casi que se iban resolviendo \"solas\" por el simple hecho de explorar como dices (algo con lo que no coincido, pero vamos a tomarlo como válido), aquí tienes que tener la intención deliberada de hacer esa tarea tediosa si o si, porque difícilmente vayas a hacer eso desinteresadamente. Menos cuando te equipas otro blade y te pide lo mismo que el anterior pero no vale que ya lo hayas hecho con ese otro blade. Es decir, un blade te pide que hables con 50 Nopons, lo haces (intencionada o casualmente) y evolucionas su afinigrama. Conseguís a otro blade que también te pide que hables con 50 Nopons y el recuento va a cero, no tiene en cuenta que lo hayas hecho con otro...Yo desde luego me hubiese divertido más evolucionar sus afinigramas disfrutando su sistema de combate que cumpliendo con ese tipo de tareas tediosas. En fin, me parece pésimamente ejecutado.</p><p></p></div><p></p></div></blockquote><p></p><p>Completamente de acuerdo, tanto el sistema de afinigrama como los logros están fatalmente implementados en este juego, nada que ver con los 2 Xenoblades anteriores. </p><p></p><p> </p><p></p><p>Este Xenoblade tiene ideas muy buenas pero casi todas las ejecuta de la forma más tediosa. Por poner un ejemplo, Zenobia me salió el último Blade (otra idea penosa, la mayoría de los Blades al azar en vez de desbloquearlos en misiones secundarias, solo unos pocos) y su afinigrama consiste en derrotar monstruos únicos. El problema es que hay que derrotarlos de nuevo y por orden, no cuentan si lo has hecho antes... Encima las lápidas que dejan no te indican ni el nombre ni nada, de nuevo otra buena idea (las lápidas) mal ejecutada porque así no valen para nada. Si vuelven a meter a los Blades (que seguramente no, en cada juego \"Blade\" significa algo distinto) espero que cambien absolutamente todo para desarrollarlos, porque así no funciona bien. </p><p></p><p> </p><p></p><p>Las misiones de mercenarios consisten en seleccionar en un menú y esperar. Sí, puedes hacer otras cosas mientras se hacen, pero cortan muchísimo el rollo cuando estás haciendo misiones secundarias que te exigen el uso de esta función. Con la misión de Úrsula directamente da la sensación de que testearon poco el juego...</p><p></p><p> </p><p></p><p>En cuanto a las competencias lo mismo, la idea es muy buena pero no se podía haber hecho de forma más pesada. Sobretodo se nota cuando exploras, cada 5 o 10 minutos te obligan a meterte en el menú para volver a configurar tus Blades. En los 2 Xenoblades anteriores tenías mayor personalización de ropas, complementos, etc y te podías tirar perfectamente media hora configurando tu equipo (en X incluso más con los Skell y los 4 miembros, aunque podías darle a un botón para que te escogiera el mejor equipo), pero era algo que hacías cada varias horas. Aquí hay parones cada pocos minutos. Da la sensación de que estás mucho más en los menús que en los 2 Xenoblades anteriores.</p><p></p><p> </p><p></p><p>En cuanto al diseño de mapas, empecé poniéndolo por encima del primer Xenoblade pero la verdad es que no lo tengo tan claro ahora. Pienso que tiene 2 titanes muy buenos (Gormot y Mor Ardain) pero el resto es bastante más simple y las zonas finales del primero estaban diseñadas de forma más laberíntica. Ya no lo comparo con X porque obviamente está a otro nivel en este sentido.</p><p></p><p> </p><p></p><p>El juego destaca en su sistema de combate (que tarda mucho en arrancar, igual unas 20 horas) y en su historia/personajes que, pese a lo que puede parecer en la primera mitad del juego, están muy bien. Obviamente vale mucho la pena, pero yo no me esperaría algo tan tocho como sus precuelas. En el resto de apartados lo veo por debajo de las 2 entrega anteriores (excepto el gráfico en comparación con el de Wii y por supuesto la BSO que es brutal). En concreto en el apartado jugable también lo veo por debajo del primero porque, si bien tiene un mejor sistema de combate, en todo lo demás no está tan bien diseñado.</p><p></p><p> </p><p></p><p>Y por cierto, sigo en mis trece. Sigo viéndolo por debajo de X en el apartado técnico. Alguna zona interior tiene muy buenas texturas pero es un juego mucho más limitado con un mapeado mucho más pequeño y con cargas. Aunque X tenía sus cosas cutres (traspasar enemigos y coches, las animaciones de los personajes en los vídeos) usaba los recursos con mucha cabeza, haciendo un apartado visual impresionante si no te ponías a mirar de cerca y encima con rendimiento perfecto. Por no mencionar que se ve más bastante más borroso (¿no se supone que van a la misma resolución?) y pega unos tirones a veces que ríete tu del Zelda en WiiU.</p><p></p><p> </p><p></p><p>Lo dicho, el juego merece la pena si te gustaron los anteriores; pero yo no me esperaría otro megatón. Por lo menos no en todo lo que no es historia/BSO. </p>\t\t\t\t\t</div>"},{"id":49195530,"author":"Kaim","registrationDate":"16 Feb 2007","publicationDate":"2018-01-08T02:15:49Z","numMessages":24161,"content":"<blockquote data-ipsquote=\"\" class=\"ipsQuote\" data-ipsquote-contentcommentid=\"49195512\" data-ipsquote-username=\"DarkJM\" data-cite=\"DarkJM\" data-ipsquote-timestamp=\"1515376230\"><div><p></p><div><p></p><p>Completamente de acuerdo, tanto el sistema de afinigrama como los logros están fatalmente implementados en este juego, nada que ver con los 2 Xenoblades anteriores. </p><p></p><p> </p><p></p><p>Este Xenoblade tiene ideas muy buenas pero casi todas las ejecuta de la forma más tediosa. Por poner un ejemplo, Zenobia me salió el último Blade (otra idea penosa, la mayoría de los Blades al azar en vez de desbloquearlos en misiones secundarias, solo unos pocos) y su afinigrama consiste en derrotar monstruos únicos. El problema es que hay que derrotarlos de nuevo y por orden, no cuentan si lo has hecho antes... Encima las lápidas que dejan no te indican ni el nombre ni nada, de nuevo otra buena idea (las lápidas) mal ejecutada porque así no valen para nada. Si vuelven a meter a los Blades (que seguramente no, en cada juego \"Blade\" significa algo distinto) espero que cambien absolutamente todo para desarrollarlos, porque así no funciona bien. </p><p></p><p> </p><p></p><p>Las misiones de mercenarios consisten en seleccionar en un menú y esperar. Sí, puedes hacer otras cosas mientras se hacen, pero cortan muchísimo el rollo cuando estás haciendo misiones secundarias que te exigen el uso de esta función. Con la misión de Úrsula directamente da la sensación de que testearon poco el juego...</p><p></p><p> </p><p></p><p>En cuanto a las competencias lo mismo, la idea es muy buena pero no se podía haber hecho de forma más pesada. Sobretodo se nota cuando exploras, cada 5 o 10 minutos te obligan a meterte en el menú para volver a configurar tus Blades. En los 2 Xenoblades anteriores tenías mayor personalización de ropas, complementos, etc y te podías tirar perfectamente media hora configurando tu equipo (en X incluso más con los Skell y los 4 miembros, aunque podías darle a un botón para que te escogiera el mejor equipo), pero era algo que hacías cada varias horas. Aquí hay parones cada pocos minutos. Da la sensación de que estás mucho más en los menús que en los 2 Xenoblades anteriores.</p><p></p><p> </p><p></p><p>En cuanto al diseño de mapas, empecé poniéndolo por encima del primer Xenoblade pero la verdad es que no lo tengo tan claro ahora. Pienso que tiene 2 titanes muy buenos (Gormot y Mor Ardain) pero el resto es bastante más simple y las zonas finales del primero estaban diseñadas de forma más laberíntica. Ya no lo comparo con X porque obviamente está a otro nivel en este sentido.</p><p></p><p> </p><p></p><p>El juego destaca en su sistema de combate (que tarda mucho en arrancar, igual unas 20 horas) y en su historia/personajes que, pese a lo que puede parecer en la primera mitad del juego, están muy bien. Obviamente vale mucho la pena, pero yo no me esperaría algo tan tocho como sus precuelas. En el resto de apartados lo veo por debajo de las 2 entrega anteriores (excepto el gráfico en comparación con el de Wii y por supuesto la BSO que es brutal). En concreto en el apartado jugable también lo veo por debajo del primero porque, si bien tiene un mejor sistema de combate, en todo lo demás no está tan bien diseñado.</p><p></p><p> </p><p></p><p>Y por cierto, sigo en mis trece. Sigo viéndolo por debajo de X en el apartado técnico. Alguna zona interior tiene muy buenas texturas pero es un juego mucho más limitado con un mapeado mucho más pequeño y con cargas. Aunque X tenía sus cosas cutres (traspasar enemigos y coches, las animaciones de los personajes en los vídeos) usaba los recursos con mucha cabeza, haciendo un apartado visual impresionante si no te ponías a mirar de cerca y encima con rendimiento perfecto. Por no mencionar que se ve más bastante más borroso (¿no se supone que van a la misma resolución?) y pega unos tirones a veces que ríete tu del Zelda en WiiU.</p><p></p><p> </p><p></p><p>Lo dicho, el juego merece la pena si te gustaron los anteriores; pero yo no me esperaría otro megatón. Por lo menos no en todo lo que no es historia/BSO. </p><p></p></div><p></p></div></blockquote><p></p><p> </p><p></p><p>Hay dos cosas que podrían medio-arreglar con actualizaciones fácilmente:</p><p></p><p> </p><p></p><p>1- Que no sea necesario equipar las blades para las competencias, con tenerlas que ya alcance. Así nos evitaríamos tener que entrar al menú cada 5 pasos como pasa en ciertas ocasiones.</p><p></p><p> </p><p></p><p>2- Meterle un bestiario, este juego lo necesita como el comer. Así al menos se solucionaría lo de volver a matar bichos. \"¿Que tengo que volver a matar a Burdiel, el asesino loco\" &gt; Bestiario &gt; Me fijo cuál es y donde se ubica &gt; Voy a por él.</p><p></p><p> </p><p></p><p>El resto de cosas ya son más difíciles de corregir mediante actualizaciones. </p>\t\t\t\t\t</div>"},{"id":49195644,"author":"religioso","registrationDate":"13 Abr 2007","publicationDate":"2018-01-08T07:29:21Z","numMessages":24091,"content":"<p>Lo del bestiario es algo nunca comprenderé. Vaya forma de complicarse la vida. Y en el primero creo que era igual. Vaya coñazo. Y muy pocas veces valía la pena hacer las misiones secundarias de matar a sabediosquécosa. Como casi todo. Hay una infinidad de cosas por hacer, pero la mayoría apesta a tedio.&nbsp; &nbsp;</p>\t\t\t\t\t</div>"},{"id":49195823,"author":"alone snake","registrationDate":"14 Sep 2005","publicationDate":"2018-01-08T09:34:13Z","numMessages":12756,"content":"<p>Lo del bestiario es algo que creo que deberian de plantearselo ya <img alt=\"X-D\" data-src=\"http://meristation.as.com/zonaforo/uploads/emoticons/default_descojone-1.gif\" src=\"http://meristation.as.com/zonaforo/applications/core/interface/js/spacer.png\"></p><br><p> </p><br><p> </p><br><p>Que si no me equivoco, en el Xenoblade de la N3DS si que lo incluyeron supongo que como incentivo por las cosas que perdia la version esta. Pero es que no han sacado ningun bestiario lo que llevamos de trilogia.</p><br><p> </p><br><p>Si pudiera ponerme en contacto con Takahashi, se lo diria. En el X te metian la enciclopedia esa pero no era buena. Es la verdadera tarea pendiente que tienen.</p><br><p> </p><br><p>Porque al final, el tema del afinigrama en este o el de las competencias, puede gustar o no, se puede mejorar y tal, pero al final, son mecanicas nuevas que han introducido en este... Bueno no tan nuevas (en el X estaban las de biologia, mecanica, arqueologia) pero si que han cambiado en muchos sentidos.  Pero lo otro es algo que lleva desde el primero <img alt=\"X-D\" data-src=\"http://meristation.as.com/zonaforo/uploads/emoticons/default_descojone-1.gif\" src=\"http://meristation.as.com/zonaforo/applications/core/interface/js/spacer.png\"></p><br><p> </p><br><p> </p><br><p> </p><br><p> </p><br><blockquote data-ipsquote=\"\" class=\"ipsQuote\" data-ipsquote-contentcommentid=\"49195468\" data-ipsquote-username=\"Kaim\" data-cite=\"Kaim\" data-ipsquote-timestamp=\"1515372201\"><div><br><div> </div><br></div></blockquote><br><p> </p><br><p>Yo no me olvido de ti.... <img alt=\"X-D\" data-src=\"http://meristation.as.com/zonaforo/uploads/emoticons/default_descojone-1.gif\" src=\"http://meristation.as.com/zonaforo/applications/core/interface/js/spacer.png\"></p><br><p> </p><br><p>Pues tengo a Boreas y Poppi, claro y con la primera una tuve que finiquitar esa \"mision\" hablando con cuatro (ya solo me faltaba esos para hablar cuando se me activo) y Boreas practicamente en cuanto se desbloqueó, directamente se activo. sin hacer nada. Y dudo mucho que hablara con siquiera 10 nopons antes de eso.</p><br>\t\t\t\t\t</div>"},{"id":49196207,"author":"Leader Protoss","registrationDate":"9 Ene 2005","publicationDate":"2018-01-08T12:09:24Z","numMessages":15965,"content":"<blockquote data-ipsquote=\"\" class=\"ipsQuote\" data-ipsquote-contentcommentid=\"49195469\" data-ipsquote-username=\"Sirya\" data-cite=\"Sirya\" data-ipsquote-timestamp=\"1515372292\"><div><p></p><div><p></p><p>Diría que es pesado de cojones, pero es que todavía resuena en mi cabeza la puta frase de Kosm.</p><p></p></div><p></p></div></blockquote><p></p><p> </p><p></p><p>- Ah, Kos, o como algunos dicen, Ko-</p><p></p><p> </p><p></p><p>- Cállese inmediatamente, HDLGP.</p>\t\t\t\t\t</div>"},{"id":49196246,"author":"Windows 2000","registrationDate":"8 Ago 2017","publicationDate":"2018-01-08T12:21:53Z","numMessages":1793,"content":"<p>Mira que odio todo lo relacionado con la pérfida Albión, pero prefiero jugar los jrpgs en inglés antes que en japo, que parecen lolis chillando todo el rato</p><br />\t\t\t\t\t</div>"},{"id":49196298,"author":"DarkJM","registrationDate":"18 Ago 2009","publicationDate":"2018-01-08T12:49:53Z","numMessages":9110,"content":"<blockquote data-ipsquote=\"\" class=\"ipsQuote\" data-ipsquote-contentcommentid=\"49196246\" data-ipsquote-username=\"Pippols\" data-cite=\"Pippols\" data-ipsquote-timestamp=\"1515414113\"><div><p></p><div><p></p><p>Mira que odio todo lo relacionado con la pérfida Albión, pero prefiero jugar los jrpgs en inglés antes que en japo, que parecen lolis chillando todo el rato</p><p></p></div><p></p></div></blockquote><p></p><p>Aunque parezca lo contrario por lo que se ve en el vídeo (que realmente es la única cagada que veo en el juego en este sentido), el doblaje en inglés en este juego es muy bueno. A mi me parece superior al japonés y determinados personajes ganan bastante con sus voces inglesas. Además tiene un detalle muy curioso, en cada titán hay un acento diferente.</p><p></p><p> </p><p></p><p>En japonés hay cosas como esto, la voz no pega con el personaje.</p><p></p><p><iframe id=\"ytplayer\" class=\"EmbeddedVideo\" type=\"text/html\" width=\"100%\" height=\"390\" frameborder=\"0\" allowfullscreen webkitallowfullscreen data-embed-src=\"https://youtube.com/embed/Qg5dF63Wvvc?html5=1&amp;fs=1\"></iframe></p>\t\t\t\t\t</div>"},{"id":49198359,"author":"Sir_Dekar","registrationDate":"7 Jul 2008","publicationDate":"2018-01-09T03:56:09Z","numMessages":54061,"content":"<blockquote data-ipsquote=\"\" class=\"ipsQuote\" data-ipsquote-contentcommentid=\"49196298\" data-ipsquote-username=\"DarkJM\" data-cite=\"DarkJM\" data-ipsquote-timestamp=\"1515415793\"><div><p></p><div><p></p><p> </p><p></p><p>En japonés hay cosas como esto, la voz no pega con el personaje.</p><p></p><p><iframe id=\"ytplayer\" class=\"EmbeddedVideo\" type=\"text/html\" width=\"100%\" height=\"390\" frameborder=\"0\" allowfullscreen webkitallowfullscreen data-embed-src=\"https://youtube.com/embed/Qg5dF63Wvvc?html5=1&amp;fs=1\"></iframe></p><p></p></div><p></p></div></blockquote><p></p><p> </p><p></p><p>Es que menudo travelo que han metido en el juego. Monolith Soft abriéndose a todas las tendencias sexuales... <img alt=\"X-D\" data-src=\"http://meristation.as.com/zonaforo/uploads/emoticons/default_descojone-1.gif\" src=\"http://meristation.as.com/zonaforo/applications/core/interface/js/spacer.png\"></p>\t\t\t\t\t</div>"},{"id":49198474,"author":"DarkJM","registrationDate":"18 Ago 2009","publicationDate":"2018-01-09T07:54:35Z","numMessages":9110,"content":"<blockquote data-ipsquote=\"\" class=\"ipsQuote\" data-ipsquote-contentcommentid=\"49198359\" data-ipsquote-username=\"Sir_Dekar\" data-cite=\"Sir_Dekar\" data-ipsquote-timestamp=\"1515470169\"><div><p> </p><p>Es que menudo travelo que han metido en el juego. Monolith Soft abriéndose a todas las tendencias sexuales... <img alt=\"X-D\" data-src=\"http://meristation.as.com/zonaforo/uploads/emoticons/default_descojone-1.gif\" src=\"http://meristation.as.com/zonaforo/applications/core/interface/js/spacer.png\"></p></div></blockquote><p>Hay un Travelo, pero no es esta...</p>\t\t\t\t\t</div>"},{"id":49198488,"author":"Choco Love","registrationDate":"1 Dic 2005","publicationDate":"2018-01-09T08:13:01Z","numMessages":12509,"content":"<p>Yo en general prefiero el japonés, pero en este caso hicieron un trabajo muy bueno con el inglés. Particularmente Nia me gusta mucho más en inglés.</p><br /><p>&nbsp;</p><br /><p>Sobre los defectos de este Xenoblade, estoy de acuerdo en que están ahí pero no en su importancia relativa. A mi modo de verlo, lo más importante en este tipo de juegos es el sistema de combate y justo después la narrativa, y en estos aspectos es brillante. Por primera vez en un Xenoblade, durante toda la historia principal, hay un buen ritmo argumental, sin largos lapsos de tiempo desprovistos de revelaciones argumentales.</p><br /><p>&nbsp;</p><br /><p>Yo expresé que se habían pasado con el HP de los enemigos, pero tiene sentido para aprovechar el sistema de combate. En el primero tenías muchas posibilidades pero abusaba de ciertas mecánicas (derribo sobre todo) y las matemáticas daban demasiado peso a los stats, hasta el punto de que subir un nivel era normalmente mucho más efectivo que luchar de otra forma. Además las sidequests eran muy repetitivas. Pero son juegos en los que las imperfecciones vienen compensadas por la magnitud.</p><br />\t\t\t\t\t</div>"}],"totalPages":3}